TOPSIS/__init__.py
TOPSIS/__main__.py
TOPSIS_Manjot-1.0.0.dist-info/LICENSE.txt
TOPSIS_Manjot-1.0.0.dist-info/METADATA
TOPSIS_Manjot-1.0.0.dist-info/WHEEL
TOPSIS_Manjot-1.0.0.dist-info/entry_points.txt
TOPSIS_Manjot-1.0.0.dist-info/top_level.txt
TOPSIS_Manjot-1.0.0.dist-info/RECORD
