Metadata-Version: 2.1
Name: TOPSIS_Manjot
Version: 1.0.0
Summary: Calculates Topsis Score and Rank them accordingly
Home-page: https://github.com/SingManjot/TOPSIS_Manjot
Author: Manjot Singh Kandhari
Author-email: smanjot444@gmail.com
License: MIT
Classifier: Programming Language :: Python :: 3
Classifier: License :: OSI Approved :: MIT License
Classifier: Operating System :: OS Independent
License-File: LICENSE.txt
